{
    "@odata.context": "/redfish/v1/$metadata#HpeServerPciDevice.HpeServerPciDevice",
    "@odata.etag": "W/\"EDEE495C\"",
    "@odata.id": "/redfish/v1/Systems/1/PCIDevices/5",
    "@odata.type": "#HpeServerPciDevice.v2_0_0.HpeServerPciDevice",
    "Id": "5",
    "Bifurcated": "BifurcationNotSupported",
    "BusNumber": 73,
    "ClassCode": 1,
    "DeviceID": 655,
    "DeviceInstance": 12,
    "DeviceLocation": "Storage Controller Slot 12",
    "DeviceNumber": 0,
    "DeviceSubInstance": 1,
    "DeviceType": "Storage Array Controller",
    "FunctionNumber": 0,
    "LocationString": "Storage Slot 12",
    "Name": "HPE SR416i-a Gen10+",
    "SegmentNumber": 0,
    "StructuredName": "RAID.Slot.12.1",
    "SubclassCode": 7,
    "SubsystemDeviceID": 732,
    "SubsystemVendorID": 5520,
    "UEFIDevicePath": "PciRoot(0x4)/Pci(0x2,0x0)/Pci(0x0,0x0)/Pci(0x0,0x0)/Pci(0x0,0x0)",
    "VendorID": 36869
}