{
    "@odata.context": "/redfish/v1/$metadata#LogEntry.LogEntry",
    "@odata.etag": "W/\"13B1261A\"",
    "@odata.id": "/redfish/v1/Systems/1/LogServices/SL/Entries/55",
    "@odata.type": "#LogEntry.v1_11_0.LogEntry",
    "Id": "55",
    "Created": "2023-04-27T00:59:24Z",
    "EntryType": "Oem",
    "Message": "iLO detected 3 unauthorized login attempts.",
    "MessageArgs": [],
    "MessageId": "56.2",
    "Name": "Security Log",
    "Oem": {
        "Hpe": {
            "@odata.context": "/redfish/v1/$metadata#HpeLogEntry.HpeLogEntry",
            "@odata.type": "#HpeLogEntry.v2_4_0.HpeLogEntry",
            "Categories": [
                "Security",
                "Administration"
            ],
            "Class": 56,
            "ClassDescription": "Denial of Service",
            "Code": 2,
            "Count": 1,
            "EventNumber": 80,
            "Severity": "Informational",
            "Updated": "2023-04-27T00:59:24Z",
            "UserAction": "Not Applicable"
        }
    },
    "OemRecordFormat": "Hpe-SL",
    "Severity": "OK"
}